quibraries/__init__.py
quibraries/arg_ops.py
quibraries/consts.py
quibraries/errors.py
quibraries/helpers.py
quibraries/http_ops.py
quibraries/py.typed
quibraries/remote_sess.py
quibraries/search.py
quibraries/search_helpers.py
quibraries/search_ops.py
quibraries/subscribe.py
quibraries/subscribe_helpers.py
quibraries/subscribe_ops.py
tests/__init__.py
tests/conftest.py
tests/test_pagination.py
tests/test_platforms.py
tests/test_projects.py
tests/test_repositories.py
tests/test_subscription.py
tests/test_users.py
quibraries-1.1.0.dist-info/LICENSE
quibraries-1.1.0.dist-info/METADATA
quibraries-1.1.0.dist-info/WHEEL
quibraries-1.1.0.dist-info/top_level.txt
quibraries-1.1.0.dist-info/RECORD
