Metadata-Version: 2.1
Name: quibraries
Version: 1.1.0
Summary: A thread-safe Python wrapper for the libraries.io API
Home-page: https://github.com/andylamp/quibraries/
Author: Andreas A. Grammenos
Author-email: axorl@quine.sh
License: MIT
Classifier: Development Status :: 5 - Production/Stable
Classifier: Programming Language :: Python :: 3.10
Classifier: Programming Language :: Python :: 3.11
Classifier: Programming Language :: Python :: 3.12
Classifier: License :: OSI Approved :: MIT License
Requires-Python: >=3.10
License-File: LICENSE
Requires-Dist: requests >=2.31.0
